__init__.py
easycalculate.py
easycalculate-0.1.5.dist-info/LICENSE
easycalculate-0.1.5.dist-info/METADATA
easycalculate-0.1.5.dist-info/WHEEL
easycalculate-0.1.5.dist-info/top_level.txt
easycalculate-0.1.5.dist-info/RECORD
