Metadata-Version: 2.1
Name: easycalculate
Version: 0.1.5
Summary: A package for calculate Math problem contain easy calculation and easy linear algebra problem, in the future author will add functions to solve easy geometry problems.
Author-email: JinXinxi <2358155969@qq.com>
Project-URL: Homepage, https://gitee.com/JXX_CODE/easycalculate
Project-URL: Bug Tracker, https://gitee.com/JXX_CODE/easycalculate/issues
Classifier: Programming Language :: Python :: 3
Classifier: License :: OSI Approved :: MIT License
Requires-Python: >=3.6
License-File: LICENSE
